drgpom/.__init__.py.un~
drgpom/__init__.py
drgpom/__init__.py~
drgpom/paths.py
drgpom/examples/__init__.py
drgpom/examples/example_population_creation.py
drgpom/examples/example_population_creation_fullsize.py
drgpom/examples/example_population_creation_midsize.py
drgpom/examples/example_population_from_parameter_file.py
drgpom/examples/example_save_all_ionic_currents.py
drgpom/examples/example_simulation.py
drgpom/examples/example_simulation_.py
drgpom/examples/example_simulation_saving_all_ionic_currents.py
drgpom/examples/examples_notebook.ipynb
drgpom/examples/vary_amp_and_gnav18.py
drgpom/examples/data/__init__.py
drgpom/examples/data/calibration_biomarkers.csv
drgpom/examples/data/example_population.pkl
drgpom/examples/data/nav18_project_parameters_5_6.csv
drgpom/examples/data/pom_parameters.csv
drgpom/examples/data/test_np.pkl
drgpom/examples/data/test_population.pkl
drgpom/examples/data/trace_1.pkl
drgpom/examples/data/trace_2.pkl
drgpom/examples/data/trace_3.pkl
drgpom/examples/data/trace_4.pkl
drgpom/examples/data/trace_5.pkl
drgpom/examples/data/trace_6.pkl
drgpom/examples/results/__init__.py
drgpom/examples/results/example_population.pkl
drgpom/examples/results/example_population_fullsize.pkl
drgpom/examples/results/example_population_small.pkl
drgpom/examples/results/results.txt
drgpom/methods/analysis.py
drgpom/methods/current_models.py
drgpom/methods/init__.py
drgpom/methods/loadneuron.py
drgpom/methods/pom.py
drgpom/methods/simulation_helpers.py
drgpom/methods/visualisation.py
drgpom/methods/biomarkers/__init__.py
drgpom/methods/biomarkers/davidson_biomarkers.py
drgpom/methods/biomarkers/neuron_biomarkers.py
drgpom/models/IRamp.mod
drgpom/models/KAtf.mod
drgpom/models/KAtf_named.mod
drgpom/models/KMtf.mod
drgpom/models/Kacw.mod
drgpom/models/Kdrcw.mod
drgpom/models/Kdrtf.mod
drgpom/models/Kleak.mod
drgpom/models/Naleak.mod
drgpom/models/Nav16bk.mod
drgpom/models/Nav16hs.mod
drgpom/models/Nav17cw.mod
drgpom/models/Nav17vw.mod
drgpom-1.0.5.dist-info/LICENSE.txt
drgpom-1.0.5.dist-info/LICENSE.txt.txt~
drgpom-1.0.5.dist-info/METADATA
drgpom-1.0.5.dist-info/WHEEL
drgpom-1.0.5.dist-info/top_level.txt
drgpom-1.0.5.dist-info/RECORD
